fatfs/wrapper.cpython-39-darwin.so
fatfs/__init__.py
fatfs/diskio.py
fatfs-0.1.2.dist-info/LICENSE.md
fatfs-0.1.2.dist-info/RECORD
fatfs-0.1.2.dist-info/WHEEL
fatfs-0.1.2.dist-info/top_level.txt
fatfs-0.1.2.dist-info/METADATA
