Metadata-Version: 2.1
Name: fatfs
Version: 0.1.2
Summary: A wrapper around ChaN's FatFS library for FAT filesystem manipulation.
Home-page: https://github.com/krakonos/fatfs-python
Author: Ladislav Laska
Author-email: krakonos@krakonos.org
Classifier: Development Status :: 2 - Pre-Alpha
Classifier: Intended Audience :: Developers
Classifier: Programming Language :: Python :: 3
Classifier: License :: OSI Approved :: MIT License
Classifier: Operating System :: OS Independent
Classifier: Topic :: Scientific/Engineering
Classifier: Topic :: Software Development :: Embedded Systems
Classifier: Topic :: Software Development :: Libraries
Classifier: Topic :: System :: Filesystems
Requires-Python: >=3.8
License-File: LICENSE.md
